idgenerator/__init__.py
idgenerator/src/__init__.py
idgenerator/src/idgenerator.py
testHello123-0.0.10.dist-info/LICENSE
testHello123-0.0.10.dist-info/METADATA
testHello123-0.0.10.dist-info/WHEEL
testHello123-0.0.10.dist-info/top_level.txt
testHello123-0.0.10.dist-info/RECORD
