Metadata-Version: 2.1
Name: testHello123
Version: 0.0.10
Summary: just hello aap
Home-page: https://github.com/pallav-acog/testPackage
Author: pallav-acog
Author-email: pallav@aganitha.ai
License: MIT
Classifier: License :: OSI Approved :: MIT License
Classifier: Programming Language :: Python :: 3.10
Classifier: Operating System :: OS Independent
Requires-Python: >=3.10
License-File: LICENSE
Provides-Extra: dev
Requires-Dist: pytest >=7.0 ; extra == 'dev'
Requires-Dist: twine >=4.0.2 ; extra == 'dev'
